tellodji/__init__.py
tellodji/live.html
tellodji/record.html
tellodji/tello.py
tellodji/tello_decor.py
tellodji/tello_error.py
tellodji/tello_web.py
tellodji-0.4.0.dist-info/LICENSE.txt
tellodji-0.4.0.dist-info/WHEEL
tellodji-0.4.0.dist-info/METADATA
tellodji-0.4.0.dist-info/RECORD
