Metadata-Version: 2.1
Name: tellodji
Version: 0.4.0
Summary: A Python library for controlling Tello drones using the 1.3 or 2.0 SDK
Home-page: https://github.com/zahtec/tellodji
License: MIT
Keywords: tello,drone,drones,sdk,dji,djitello,interface,video,ffmpeg,tellovideo,tellodji,djitello
Author: zahtec
Requires-Python: >=3.10,<4.0
Classifier: Intended Audience :: Developers
Classifier: License :: OSI Approved :: MIT License
Classifier: Natural Language :: English
Classifier: Operating System :: OS Independent
Classifier: Programming Language :: Python :: 3
Classifier: Programming Language :: Python :: 3.10
Classifier: Programming Language :: Python :: 3.10
Classifier: Typing :: Typed
Requires-Dist: pillow (>=9.2.0,<10.0.0)
Project-URL: Bug Tracker, https://github.com/zahtec/tellodji/issues
Project-URL: Documentation, https://github.com/zahtec/tellodji/wiki
Project-URL: Repository, https://github.com/zahtec/tellodji
